{
    "2023-10-01": {
        "MP10": 23,
        "MP2.5": "NA",
        "O3": 19,
        "CO": "NA",
        "NO2": "NA",
        "SO2": "NA",
        "IQAr": 18,
        "classificacao": "Boa"
    },
    "2023-10-02": {
        "MP10": 31,
        "MP2.5": "NA",
        "O3": 29,
        "CO": "NA",
        "NO2": "NA",
        "SO2": "NA",
        "IQAr": 25,
        "classificacao": "Boa"
    },
    "2023-10-03": {
        "MP10": 34,
        "MP2.5": "NA",
        "O3": 34,
        "CO": "NA",
        "NO2": "NA",
        "SO2": "NA",
        "IQAr": 27,
        "classificacao": "Boa"
    },
    "2023-10-04": {
        "MP10": 35,
        "MP2.5": "NA",
        "O3": 45,
        "CO": "NA",
        "NO2": "NA",
        "SO2": "NA",
        "IQAr": 28,
        "classificacao": "Boa"
    },
    "2023-10-05": {
        "MP10": 42,
        "MP2.5": "NA",
        "O3": 36,
        "CO": "NA",
        "NO2": "NA",
        "SO2": "NA",
        "IQAr": 34,
        "classificacao": "Boa"
    },
    "2023-10-06": {
        "MP10": 32,
        "MP2.5": "NA",
        "O3": 41,
        "CO": "NA",
        "NO2": "NA",
        "SO2": "NA",
        "IQAr": 26,
        "classificacao": "Boa"
    },
    "2023-10-07": {
        "MP10": 44,
        "MP2.5": "NA",
        "O3": 44,
        "CO": "NA",
        "NO2": "NA",
        "SO2": "NA",
        "IQAr": 35,
        "classificacao": "Boa"
    },
    "2023-10-08": {
        "MP10": 26,
        "MP2.5": "NA",
        "O3": 50,
        "CO": "NA",
        "NO2": "NA",
        "SO2": "NA",
        "IQAr": 21,
        "classificacao": "Boa"
    },
    "2023-10-09": {
        "MP10": 31,
        "MP2.5": "NA",
        "O3": 40,
        "CO": "NA",
        "NO2": "NA",
        "SO2": "NA",
        "IQAr": 25,
        "classificacao": "Boa"
    },
    "2023-10-10": {
        "MP10": 25,
        "MP2.5": "NA",
        "O3": 43,
        "CO": "NA",
        "NO2": "NA",
        "SO2": "NA",
        "IQAr": 20,
        "classificacao": "Boa"
    },
    "2023-10-11": {
        "MP10": 25,
        "MP2.5": "NA",
        "O3": 36,
        "CO": "NA",
        "NO2": "NA",
        "SO2": "NA",
        "IQAr": 20,
        "classificacao": "Boa"
    },
    "2023-10-12": {
        "MP10": 26,
        "MP2.5": "NA",
        "O3": 42,
        "CO": "NA",
        "NO2": "NA",
        "SO2": "NA",
        "IQAr": 21,
        "classificacao": "Boa"
    },
    "2023-10-13": {
        "MP10": 18,
        "MP2.5": "NA",
        "O3": 40,
        "CO": "NA",
        "NO2": "NA",
        "SO2": "NA",
        "IQAr": 16,
        "classificacao": "Boa"
    },
    "2023-10-14": {
        "MP10": 19,
        "MP2.5": "NA",
        "O3": 36,
        "CO": "NA",
        "NO2": "NA",
        "SO2": "NA",
        "IQAr": 15,
        "classificacao": "Boa"
    },
    "2023-10-15": {
        "MP10": 30,
        "MP2.5": "NA",
        "O3": 30,
        "CO": "NA",
        "NO2": "NA",
        "SO2": "NA",
        "IQAr": 24,
        "classificacao": "Boa"
    },
    "2023-10-16": {
        "MP10": "NA",
        "MP2.5": "NA",
        "O3": 26,
        "CO": "NA",
        "NO2": "NA",
        "SO2": "NA",
        "IQAr": 10,
        "classificacao": "Boa"
    },
    "2023-10-17": {
        "MP10": 25,
        "MP2.5": "NA",
        "O3": 58,
        "CO": "NA",
        "NO2": "NA",
        "SO2": "NA",
        "IQAr": 23,
        "classificacao": "Boa"
    },
    "2023-10-18": {
        "MP10": 38,
        "MP2.5": "NA",
        "O3": 37,
        "CO": "NA",
        "NO2": "NA",
        "SO2": "NA",
        "IQAr": 30,
        "classificacao": "Boa"
    },
    "2023-10-19": {
        "MP10": 43,
        "MP2.5": "NA",
        "O3": 42,
        "CO": "NA",
        "NO2": "NA",
        "SO2": "NA",
        "IQAr": 34,
        "classificacao": "Boa"
    },
    "2023-10-20": {
        "MP10": 37,
        "MP2.5": "NA",
        "O3": 33,
        "CO": "NA",
        "NO2": "NA",
        "SO2": "NA",
        "IQAr": 30,
        "classificacao": "Boa"
    },
    "2023-10-21": {
        "MP10": 30,
        "MP2.5": "NA",
        "O3": 33,
        "CO": "NA",
        "NO2": "NA",
        "SO2": "NA",
        "IQAr": 24,
        "classificacao": "Boa"
    },
    "2023-10-22": {
        "MP10": 25,
        "MP2.5": "NA",
        "O3": 33,
        "CO": "NA",
        "NO2": "NA",
        "SO2": "NA",
        "IQAr": 20,
        "classificacao": "Boa"
    },
    "2023-10-23": {
        "MP10": 30,
        "MP2.5": "NA",
        "O3": 35,
        "CO": "NA",
        "NO2": "NA",
        "SO2": "NA",
        "IQAr": 24,
        "classificacao": "Boa"
    },
    "2023-10-24": {
        "MP10": 39,
        "MP2.5": "NA",
        "O3": 46,
        "CO": "NA",
        "NO2": "NA",
        "SO2": "NA",
        "IQAr": 31,
        "classificacao": "Boa"
    },
    "2023-10-25": {
        "MP10": 29,
        "MP2.5": "NA",
        "O3": 35,
        "CO": "NA",
        "NO2": "NA",
        "SO2": "NA",
        "IQAr": 23,
        "classificacao": "Boa"
    },
    "2023-10-26": {
        "MP10": 26,
        "MP2.5": "NA",
        "O3": 35,
        "CO": "NA",
        "NO2": "NA",
        "SO2": "NA",
        "IQAr": 21,
        "classificacao": "Boa"
    },
    "2023-10-27": {
        "MP10": 27,
        "MP2.5": "NA",
        "O3": 33,
        "CO": "NA",
        "NO2": "NA",
        "SO2": "NA",
        "IQAr": 22,
        "classificacao": "Boa"
    },
    "2023-10-28": {
        "MP10": 30,
        "MP2.5": "NA",
        "O3": 25,
        "CO": "NA",
        "NO2": "NA",
        "SO2": "NA",
        "IQAr": 24,
        "classificacao": "Boa"
    },
    "2023-10-29": {
        "MP10": 33,
        "MP2.5": "NA",
        "O3": 26,
        "CO": "NA",
        "NO2": "NA",
        "SO2": "NA",
        "IQAr": 26,
        "classificacao": "Boa"
    },
    "2023-10-30": {
        "MP10": 22,
        "MP2.5": "NA",
        "O3": 55,
        "CO": "NA",
        "NO2": "NA",
        "SO2": "NA",
        "IQAr": 22,
        "classificacao": "Boa"
    },
    "2023-10-31": {
        "MP10": 29,
        "MP2.5": "NA",
        "O3": 57,
        "CO": "NA",
        "NO2": "NA",
        "SO2": "NA",
        "IQAr": 23,
        "classificacao": "Boa"
    }
}